tests/__init__.py
tests/test_burcat.py
tests/test_combustion.py
tests/test_iapws.py
tests/test_janaf.py
tests/test_units.py
tests/test_wark.py
thermochem/BURCAT_THR.xml
thermochem/JANAF_index.txt
thermochem/__init__.py
thermochem/burcat.py
thermochem/codata.py
thermochem/combustion.py
thermochem/constants.py
thermochem/iapws.py
thermochem/janaf.py
thermochem/psicrometry.py
thermochem/units.py
thermochem-0.9.0.dist-info/licenses/AUTHORS.rst
thermochem-0.9.0.dist-info/licenses/LICENSE
thermochem-0.9.0.dist-info/METADATA
thermochem-0.9.0.dist-info/WHEEL
thermochem-0.9.0.dist-info/top_level.txt
thermochem-0.9.0.dist-info/RECORD
